memorygenerator/__init__.py
memorygenerator/__main__.py
memorygenerator/generator.py
tests/__init__.py
tests/test_generator.py
memorygenerator-0.1.0.dist-info/METADATA
memorygenerator-0.1.0.dist-info/WHEEL
memorygenerator-0.1.0.dist-info/entry_points.txt
memorygenerator-0.1.0.dist-info/top_level.txt
memorygenerator-0.1.0.dist-info/RECORD
