Metadata-Version: 2.1
Name: memorygenerator
Version: 0.1.0
Summary: A tool for improving code quality by analyzing and refactoring project code.
Home-page: https://github.com/yuna-musashino/refactortool
Author: Yuna Suzuki
Author-email: s2222077@stu.musashino-u.ac.jp
Classifier: Programming Language :: Python :: 3
Classifier: License :: OSI Approved :: MIT License
Classifier: Operating System :: OS Independent
Requires-Python: >=3.6
